fscacher.py
semantic_fscacher-0.3.0.dist-info/LICENSE
semantic_fscacher-0.3.0.dist-info/METADATA
semantic_fscacher-0.3.0.dist-info/WHEEL
semantic_fscacher-0.3.0.dist-info/top_level.txt
semantic_fscacher-0.3.0.dist-info/RECORD
