Metadata-Version: 2.1
Name: semantic-fscacher
Version: 0.3.0
Summary: File system based caching
Home-page: https://github.com/pnsaevik/fscacher
Author: Pål Næverlid Sævik
Author-email: pnsaevik@gmail.com
License: MIT
Platform: UNKNOWN
Classifier: Programming Language :: Python :: 3
Classifier: Programming Language :: Python :: 3.6
Classifier: Programming Language :: Python :: 3.7
Classifier: Programming Language :: Python :: 3.8
Classifier: Programming Language :: Python :: 3.9
Classifier: License :: OSI Approved :: MIT License
Classifier: Operating System :: OS Independent
Requires-Python: >=3.6
